{
  "democontent": {
    "coverstory": {
      "data": "coverstory",
      "free": "covernews",
      "premium": "covernews-pro",
      "demodata": {
        "default": {
          "name": "CoverStory",
          "catgory": "General",
          "slug": "coverstory",
          "preview": "https://demo.afthemes.com/covernews/coverstory/"
        }
      }
    },
    "newscover": {
      "data": "newscover",
      "free": "covernews",
      "premium": "covernews-pro",
      "demodata": {
        "default": {
          "name": "NewsCover",
          "catgory": "Dark",
          "slug": "newscover",
          "preview": "https://demo.afthemes.com/covernews/newscover/"
        }
      }
    },
    "hardnews": {
      "data": "hardnews",
      "free": "covernews",
      "premium": "covernews-pro",
      "demodata": {
        "default": {
          "name": "HardNews",
          "catgory": "General",
          "slug": "hardnews",
          "preview": "https://demo.afthemes.com/covernews/hardnews/"
        }
      }
    },
    "daily-newscast": {
      "data": "daily-newscast",
      "free": "covernews",
      "premium": "covernews-pro",
      "demodata": {
        "default": {
          "name": "Daily Newscast",
          "catgory": "General",
          "slug": "daily-newscast",
          "preview": "https://demo.afthemes.com/covernews/daily-newscast/"
        }
      }
    },
    "covermag": {
      "data": "covermag",
      "free": "covernews",
      "premium": "covernews-pro",
      "demodata": {
        "default": {
          "name": "CoverMag",
          "catgory": "General",
          "slug": "covermag",
          "preview": "https://demo.afthemes.com/covernews/covermag/"
        }
      }
    },
    "newsport": {
      "data": "newsport",
      "free": "covernews",
      "premium": "covernews-pro",
      "demodata": {
        "default": {
          "name": "Newsport",
          "catgory": "General",
          "slug": "newsport",
          "preview": "https://demo.afthemes.com/covernews/newsport/"
        }
      }
    },
    "newswords": {
      "data": "newswords",
      "free": "covernews",
      "premium": "covernews-pro",
      "demodata": {
        "default": {
          "name": "NewsWords",
          "catgory": "General",
          "slug": "newswords",
          "preview": "https://demo.afthemes.com/covernews/newswords/"
        }
      }
    },
    "newsquare": {
      "data": "newsquare",
      "free": "covernews",
      "premium": "covernews-pro",
      "demodata": {
        "default": {
          "name": "NewsQuare",
          "catgory": "General",
          "slug": "newsquare",
          "preview": "https://demo.afthemes.com/covernews/newsquare/"
        }
      }
    },
    "covernews": {
      "data": "covernews",
      "free": "",
      "premium": "covernews-pro",
      "demodata": {
        "default": {
          "name": "CoverNews",
          "catgory": "General",
          "slug": "covernews",
          "preview": "https://demo.afthemes.com/covernews/"
        },
        "sport": {
          "name": "Sport",
          "catgory": "Sport",
          "slug": "sport",
          "preview": "https://demo.afthemes.com/covernews/sport/"
        },
        "covid": {
          "name": "Covid 19",
          "catgory": "Elementor",
          "slug": "covid",
          "preview": "https://demo.afthemes.com/covernews/covid/",
          "plugins": "elementor,elespare"
        },
        "fashion": {
          "name": "Fashion",
          "catgory": "Fashion",
          "slug": "fashion",
          "preview": "https://demo.afthemes.com/covernews/fashion/"
        },
        "crypto-news": {
          "name": "Crypto News",
          "catgory": "Business",
          "slug": "crypto-news",
          "preview": "https://demo.afthemes.com/covernews/crypto-news/"
        },
        "arabic-news": {
          "name": "Arabic News",
          "catgory": "General",
          "slug": "arabic-news",
          "preview": "https://demo.afthemes.com/covernews/arabic-news/"
        },
        "china-news": {
          "name": "China News",
          "catgory": "General",
          "slug": "china-news",
          "preview": "https://demo.afthemes.com/covernews/china-news/"
        },
        "business": {
          "name": "Business",
          "catgory": "Business",
          "slug": "business",
          "preview": "https://demo.afthemes.com/covernews/business/"
        },
        "ornament": {
          "name": "Ornament",
          "catgory": "Elementor",
          "slug": "ornament",
          "preview": "https://demo.afthemes.com/covernews/ornament/",
          "plugins": "elementor,elespare"
        },
        "general": {
          "name": "General",
          "catgory": "Elementor",
          "slug": "general",
          "preview": "https://demo.afthemes.com/covernews/general/",
          "plugins": "elementor,elespare"
        },
        "gadgets": {
          "name": "Gadgets",
          "catgory": "Business",
          "slug": "gadgets",
          "preview": "https://demo.afthemes.com/covernews/gadgets/"
        },
        "wedding": {
          "name": "Wedding",
          "catgory": "Blog",
          "slug": "wedding",
          "preview": "https://demo.afthemes.com/covernews/wedding/"
        },
        "music": {
          "name": "Music",
          "catgory": "Elementor",
          "slug": "music",
          "preview": "https://demo.afthemes.com/covernews/music/",
          "plugins": "elementor,elespare"
        },
        "vegetables": {
          "name": "Vegetables",
          "catgory": "Elementor",
          "slug": "vegetables",
          "preview": "https://demo.afthemes.com/covernews/vegetables/",
          "plugins": "elementor,elespare"
        }
      }
    },
    "covernews-pro": {
      "data": "covernews-pro",
      "free": "covernews",
      "premium": "",
      "demodata": {
        "default-pro": {
          "name": "CoverNews Pro",
          "catgory": "General",
          "slug": "covernews",
          "preview": "https://demo.afthemes.com/covernews-pro/"
        },
        "sport-pro": {
          "name": "Sport Pro",
          "catgory": "Sport",
          "slug": "sport",
          "preview": "https://demo.afthemes.com/covernews-pro/sport-pro/"
        },
        "fashion-pro": {
          "name": "Fashion Pro",
          "catgory": "Fashion",
          "slug": "fashion",
          "preview": "https://demo.afthemes.com/covernews-pro/fashion-pro/"
        },
        "beauty-mag-pro": {
          "name": "Beauty Pro",
          "catgory": "Fashion",
          "slug": "beauty-mag",
          "preview": "https://demo.afthemes.com/covernews-pro/beauty-mag/"
        },
        "business-pro": {
          "name": "Business Pro",
          "catgory": "Business",
          "slug": "business",
          "preview": "https://demo.afthemes.com/covernews-pro/business-pro/"
        },
        "athletics-mag": {
          "name": "Athletics Mag",
          "catgory": "Sport",
          "slug": "athletics-mag",
          "preview": "https://demo.afthemes.com/covernews-pro/athletics-mag/"
        },
        "classic-pro": {
          "name": "Classic Pro",
          "catgory": "General",
          "slug": "classic",
          "preview": "https://demo.afthemes.com/covernews-pro/classic-pro/"
        },
        "gadgets-pro": {
          "name": "Gadgets Pro",
          "catgory": "Business",
          "slug": "gadgets",
          "preview": "https://demo.afthemes.com/covernews-pro/gadgets-pro/"
        },
        "general-news-pro": {
          "name": "General Pro",
          "catgory": "General",
          "slug": "general-news",
          "preview": "https://demo.afthemes.com/covernews-pro/general-news/"
        },
        "minimal-pro": {
          "name": "Minimal Pro",
          "catgory": "Blog",
          "slug": "minimal",
          "preview": "https://demo.afthemes.com/covernews-pro/minimal-pro/"
        },
        "onlinenews-pro": {
          "name": "Online News Pro",
          "catgory": "General",
          "slug": "online-news",
          "preview": "https://demo.afthemes.com/covernews-pro/online-news/"
        },
        "topnews-pro": {
          "name": "Top News Pro",
          "catgory": "General",
          "slug": "top-news",
          "preview": "https://demo.afthemes.com/covernews-pro/top-news/"
        },
        "travel-pro": {
          "name": "Travel Pro",
          "catgory": "Blog",
          "slug": "travel",
          "preview": "https://demo.afthemes.com/covernews-pro/travel-pro/"
        },
        "wedding-pro": {
          "name": "Wedding Pro",
          "catgory": "Blog",
          "slug": "wedding",
          "preview": "https://demo.afthemes.com/covernews-pro/wedding-pro/"
        },
        "gym-blog": {
          "name": "Gym Blog",
          "catgory": "Blog",
          "slug": "gym-blog",
          "preview": "https://demo.afthemes.com/covernews-pro/gym-blog/",
          "plugins": "elementor,elespare"
        },
        "crypto-news": {
          "name": "Crypto News",
          "catgory": "Business",
          "slug": "crypto-news",
          "preview": "https://demo.afthemes.com/covernews-pro/crypto-news/"
        },
        "arabic-news": {
          "name": "Arabic News",
          "catgory": "General",
          "slug": "arabic-news",
          "preview": "https://demo.afthemes.com/covernews-pro/arabic-news/"
        },
        "china-news": {
          "name": "China News",
          "catgory": "General",
          "slug": "china-news",
          "preview": "https://demo.afthemes.com/covernews-pro/china-news/"
        }
      }
    },
    "newsever": {
      "data": "newsever",
      "free": "",
      "premium": "newsever-pro",
      "demodata": {
        "default": {
          "name": "Newsever",
          "catgory": "General",
          "slug": "newsever",
          "preview": "https://demo.afthemes.com/newsever/"
        },
        "light": {
          "name": "Light",
          "catgory": "General",
          "slug": "light",
          "preview": "https://demo.afthemes.com/newsever/light/"
        },
        "dark": {
          "name": "Dark",
          "catgory": "General",
          "slug": "dark",
          "preview": "https://demo.afthemes.com/newsever/dark/"
        },
        "classic": {
          "name": "Classic",
          "catgory": "General",
          "slug": "classic",
          "preview": "https://demo.afthemes.com/newsever/classic/"
        },
        "fashion": {
          "name": "Fashion",
          "catgory": "Fashion",
          "slug": "fashion",
          "preview": "https://demo.afthemes.com/newsever/fashion/"
        },
        "sport": {
          "name": "Sport",
          "catgory": "Sport",
          "slug": "sport",
          "preview": "https://demo.afthemes.com/newsever/sport/"
        },
        "crypto-news": {
          "name": "Crypto News",
          "catgory": "Business",
          "slug": "crypto-news",
          "preview": "https://demo.afthemes.com/newsever/crypto-news/"
        },
        "arabic-news": {
          "name": "Arabic News",
          "catgory": "General",
          "slug": "arabic-news",
          "preview": "https://demo.afthemes.com/newsever/arabic-news/"
        },
        "china-news": {
          "name": "China News",
          "catgory": "General",
          "slug": "china-news",
          "preview": "https://demo.afthemes.com/newsever/china-news/"
        },
        "bikes": {
          "name": "Bikes",
          "catgory": "Elementor",
          "slug": "bikes",
          "preview": "https://demo.afthemes.com/newsever/bikes/",
          "plugins": "elementor,elespare"
        },
        "fitness": {
          "name": "Fitness",
          "catgory": "Elementor",
          "slug": "fitness",
          "preview": "https://demo.afthemes.com/newsever/fitness/",
          "plugins": "elementor,elespare"
        },
        "gadgets": {
          "name": "Gadgets",
          "catgory": "Elementor",
          "slug": "gadgets",
          "preview": "https://demo.afthemes.com/newsever/gadgets/",
          "plugins": "elementor,elespare"
        },
        "restaurant": {
          "name": "Restaurant",
          "catgory": "Elementor",
          "slug": "restaurant",
          "preview": "https://demo.afthemes.com/newsever/restaurant/",
          "plugins": "elementor,elespare"
        },
        "vogue": {
          "name": "Vogue",
          "catgory": "Elementor",
          "slug": "vogue",
          "preview": "https://demo.afthemes.com/newsever/vogue/",
          "plugins": "elementor,elespare"
        }
      }
    },
    "newsever-pro": {
      "data": "newsever-pro",
      "free": "newsever",
      "premium": "",
      "demodata": {
        "default": {
          "name": "Newsever Pro",
          "catgory": "General",
          "slug": "newsever-pro",
          "preview": "https://demo.afthemes.com/newsever-pro/"
        },
        "light": {
          "name": "Light Pro",
          "catgory": "General",
          "slug": "light",
          "preview": "https://demo.afthemes.com/newsever-pro/light/"
        },
        "dark": {
          "name": "Dark Pro",
          "catgory": "General",
          "slug": "dark",
          "preview": "https://demo.afthemes.com/newsever-pro/dark/"
        },
        "classic": {
          "name": "Classic Pro",
          "catgory": "General",
          "slug": "classic",
          "preview": "https://demo.afthemes.com/newsever-pro/classic/"
        },
        "fashion": {
          "name": "Fashion Pro",
          "catgory": "Fashion",
          "slug": "fashion",
          "preview": "https://demo.afthemes.com/newsever-pro/fashion/"
        },
        "sport": {
          "name": "Sport Pro",
          "catgory": "Sport",
          "slug": "sport",
          "preview": "https://demo.afthemes.com/newsever-pro/sport/"
        },
        "gadgets": {
          "name": "Gadgets Pro",
          "catgory": "Business",
          "slug": "gadgets",
          "preview": "https://demo.afthemes.com/newsever-pro/gadgets/"
        },
        "business": {
          "name": "Business Pro",
          "catgory": "Business",
          "slug": "business",
          "preview": "https://demo.afthemes.com/newsever-pro/business/"
        },
        "masonry": {
          "name": "Masonry Pro",
          "catgory": "Blog",
          "slug": "masonry",
          "preview": "https://demo.afthemes.com/newsever-pro/masonry/"
        },
        "recipe": {
          "name": "Recipe Pro",
          "catgory": "Blog",
          "slug": "recipe",
          "preview": "https://demo.afthemes.com/newsever-pro/recipe/"
        },
        "lifestyle": {
          "name": "Lifestyle Pro",
          "catgory": "Blog",
          "slug": "lifestyle",
          "preview": "https://demo.afthemes.com/newsever-pro/lifestyle/"
        },
        "travel": {
          "name": "Travel Pro",
          "catgory": "Blog",
          "slug": "travel",
          "preview": "https://demo.afthemes.com/newsever-pro/travel/"
        }
      }
    },
    "newsium": {
      "data": "newsium",
      "free": "",
      "premium": "newsium-pro",
      "demodata": {
        "default": {
          "name": "Newsium",
          "catgory": "General",
          "slug": "newsium",
          "preview": "https://demo.afthemes.com/newsium/"
        },
        "classic": {
          "name": "Classic",
          "catgory": "General",
          "slug": "classic",
          "preview": "https://demo.afthemes.com/newsium/classic/"
        },
        "fashion": {
          "name": "Fashion",
          "catgory": "Fashion",
          "slug": "fashion",
          "preview": "https://demo.afthemes.com/newsium/fashion/"
        },
        "sports": {
          "name": "Sport",
          "catgory": "Sport",
          "slug": "sports",
          "preview": "https://demo.afthemes.com/newsium/sports/"
        },
        "lifestyle": {
          "name": "Lifestyle",
          "catgory": "Blog",
          "slug": "lifestyle",
          "preview": "https://demo.afthemes.com/newsium/lifestyle/"
        },
        "gadgets": {
          "name": "Gadgets",
          "catgory": "Business",
          "slug": "gadgets",
          "preview": "https://demo.afthemes.com/newsium/gadgets/"
        },
        "crypto-news": {
          "name": "Crypto News",
          "catgory": "Business",
          "slug": "crypto-news",
          "preview": "https://demo.afthemes.com/newsium/crypto-news/"
        },
        "arabic-news": {
          "name": "Arabic News",
          "catgory": "General",
          "slug": "arabic-news",
          "preview": "https://demo.afthemes.com/newsium/arabic-news/"
        },
        "china-news": {
          "name": "China News",
          "catgory": "general",
          "slug": "china-news",
          "preview": "https://demo.afthemes.com/newsium/china-news/"
        },
        "cars-blog": {
          "name": "Cars Blog",
          "catgory": "Elementor",
          "slug": "cars-blog",
          "preview": "https://demo.afthemes.com/newsium/cars-blog/",
          "plugins": "elementor,elespare"
        },
        "fitness-blog": {
          "name": "Fitness Blog",
          "catgory": "Elementor",
          "slug": "fitness-blog",
          "preview": "https://demo.afthemes.com/newsium/fitness-blog/",
          "plugins": "elementor,elespare"
        },
        "food-blog": {
          "name": "Food Blog",
          "catgory": "Elementor",
          "slug": "food-blog",
          "preview": "https://demo.afthemes.com/newsium/food-blog/",
          "plugins": "elementor,elespare"
        },
        "travel-blog": {
          "name": "Travel Blog",
          "catgory": "Elementor",
          "slug": "travel-blog",
          "preview": "https://demo.afthemes.com/newsium/travel-blog/",
          "plugins": "elementor,elespare"
        },
        "wedding": {
          "name": "Wedding",
          "catgory": "Elementor",
          "slug": "wedding",
          "preview": "https://demo.afthemes.com/newsium/wedding/",
          "plugins": "elementor,elespare"
        }
      }
    },
    "newsium-pro": {
      "data": "newsium-pro",
      "free": "newsium",
      "premium": "",
      "demodata": {
        "default": {
          "name": "Newsium Pro",
          "catgory": "General",
          "slug": "newsium-pro",
          "preview": "https://demo.afthemes.com/newsium-pro/"
        },
        "light": {
          "name": "Light Pro",
          "catgory": "General",
          "slug": "newsium-light",
          "preview": "https://demo.afthemes.com/newsium-pro/newsium-light/"
        },
        "dark": {
          "name": "Dark Pro",
          "catgory": "General",
          "slug": "newsium-dark",
          "preview": "https://demo.afthemes.com/newsium-pro/newsium-dark/"
        },
        "classic": {
          "name": "Classic Pro",
          "catgory": "General",
          "slug": "classic-pro",
          "preview": "https://demo.afthemes.com/newsium-pro/classic-pro/"
        },
        "fashion": {
          "name": "Fashion Pro",
          "catgory": "Fashion",
          "slug": "fashion-pro",
          "preview": "https://demo.afthemes.com/newsium-pro/fashion-pro/"
        },
        "sport": {
          "name": "Sport Pro",
          "catgory": "Sport",
          "slug": "sport-pro",
          "preview": "https://demo.afthemes.com/newsium-pro/sport-pro/"
        },
        "gadgets": {
          "name": "Gadgets Pro",
          "catgory": "Business",
          "slug": "gadgets-pro",
          "preview": "https://demo.afthemes.com/newsium-pro/gadgets-pro/"
        },
        "lifestyle": {
          "name": "Lifestyle Pro",
          "catgory": "Blog",
          "slug": "lifestyle-pro",
          "preview": "https://demo.afthemes.com/newsium-pro/lifestyle-pro/"
        }
      }
    },
    "magcess": {
      "data": "magcess",
      "free": "newsphere",
      "premium": "newsphere-pro",
      "demodata": {
        "default": {
          "name": "Magcess",
          "catgory": "General",
          "slug": "magcess",
          "preview": "https://demo.afthemes.com/newsphere/magcess/"
        }
      }
    },
    "newspin": {
      "data": "newspin",
      "free": "newsphere",
      "premium": "newsphere-pro",
      "demodata": {
        "default": {
          "name": "Newspin",
          "catgory": "General",
          "slug": "newspin",
          "preview": "https://demo.afthemes.com/newsphere/newspin/"
        }
      }
    }
    ,
    "sportion": {
      "data": "sportion",
      "free": "newsphere",
      "premium": "newsphere-pro",
      "demodata": {
        "default": {
          "name": "Sportion",
          "catgory": "Sport",
          "slug": "sportion",
          "preview": "https://demo.afthemes.com/newsphere/sportion/"
        }
      }
    },
    "newsphere": {
      "data": "newsphere",
      "free": "",
      "premium": "newsphere-pro",
      "demodata": {
        "default": {
          "name": "Newsphere",
          "catgory": "General",
          "slug": "newsphere",
          "preview": "https://demo.afthemes.com/newsphere/"
        },
        "fashion": {
          "name": "Fashion",
          "catgory": "Fashion",
          "slug": "fashion",
          "preview": "https://demo.afthemes.com/newsphere/fashion/"
        },
        "sport": {
          "name": "Sport",
          "catgory": "Sport",
          "slug": "sport",
          "preview": "https://demo.afthemes.com/newsphere/sport/"
        },
        "crypto-news": {
          "name": "Crypto News",
          "catgory": "Business",
          "slug": "crypto-news",
          "preview": "https://demo.afthemes.com/newsphere/crypto-news/"
        },
        "arabic-news": {
          "name": "Arabic News",
          "catgory": "General",
          "slug": "arabic-news",
          "preview": "https://demo.afthemes.com/newsphere/arabic-news/"
        },
        "china-news": {
          "name": "China News",
          "catgory": "General",
          "slug": "china-news",
          "preview": "https://demo.afthemes.com/newsphere/china-news/"
        }
      }
    },
    "newsphere-pro": {
      "data": "newsphere-pro",
      "free": "newsphere",
      "premium": "",
      "demodata": {
        "default": {
          "name": "Newsphere Pro",
          "catgory": "General",
          "slug": "newsphere-pro",
          "preview": "https://demo.afthemes.com/newsphere-pro/"
        },
        "light": {
          "name": "Light Pro",
          "catgory": "General",
          "slug": "light",
          "preview": "https://demo.afthemes.com/newsphere-pro/light/"
        },
        "dark": {
          "name": "Dark Pro",
          "catgory": "General",
          "slug": "dark",
          "preview": "https://demo.afthemes.com/newsphere-pro/dark/"
        },
        "fashion": {
          "name": "Fashion Pro",
          "catgory": "Fashion",
          "slug": "fashion-pro",
          "preview": "https://demo.afthemes.com/newsphere-pro/fashion-pro/"
        },
        "sport": {
          "name": "Sport Pro",
          "catgory": "Sport",
          "slug": "sport-pro",
          "preview": "https://demo.afthemes.com/newsphere-pro/sport-pro/"
        },
        "masonry": {
          "name": "Masonry Pro",
          "catgory": "Blog",
          "slug": "masonry-pro",
          "preview": "https://demo.afthemes.com/newsphere-pro/masonry-pro/"
        },
        "minimal": {
          "name": "Minimal Pro",
          "catgory": "Blog",
          "slug": "minimal-pro",
          "preview": "https://demo.afthemes.com/newsphere-pro/minimal-pro/"
        },
        "recipe": {
          "name": "Recipe Pro",
          "catgory": "Blog",
          "slug": "recipe-pro",
          "preview": "https://demo.afthemes.com/newsphere-pro/recipe-pro/"
        },
        "travel": {
          "name": "Travel Pro",
          "catgory": "Blog",
          "slug": "travel-pro",
          "preview": "https://demo.afthemes.com/newsphere-pro/travel-pro/"
        }
      }
    },
    "storeship": {
      "data": "storeship",
      "free": "",
      "premium": "storeship-pro",
      "demodata": {
        "default": {
          "name": "Storeship",
          "catgory": "General",
          "slug": "storeship",
          "preview": "https://demo.afthemes.com/storeship/"
        },
        "fashion": {
          "name": "Fashion",
          "catgory": "Fashion",
          "slug": "fashion",
          "preview": "https://demo.afthemes.com/storeship/fashion/"
        },
        "furniture": {
          "name": "Furniture",
          "catgory": "Furniture",
          "slug": "furniture",
          "preview": "https://demo.afthemes.com/storeship/furniture/"
        }
      }
    },
    "foodshop": {
      "data": "foodshop",
      "free": "storeship",
      "premium": "storeship-pro",
      "demodata": {
        "default": {
          "name": "FoodShop",
          "catgory": "Food and Beverage",
          "slug": "foodshop",
          "preview": "https://demo.afthemes.com/storeship/foodshop/"
        }
      }
    },    
    "storeship-pro": {
      "data": "storeship-pro",
      "free": "storeship",
      "premium": "",
      "demodata": {
        "default": {
          "name": "Storeship Pro",
          "catgory": "General",
          "slug": "storeship-pro",
          "preview": "https://demo.afthemes.com/storeship-pro/"
        },
        "liquor": {
          "name": "Liquor Pro",
          "catgory": "Food and Beverage",
          "slug": "liquor",
          "preview": "https://demo.afthemes.com/storeship-pro/liquor/"
        },
        "retailer": {
          "name": "Retailer Pro",
          "catgory": "General",
          "slug": "retailer",
          "preview": "https://demo.afthemes.com/storeship-pro/retailer/"
        },
        "fashion": {
          "name": "Fashion Pro",
          "catgory": "Fashion",
          "slug": "fashion",
          "preview": "https://demo.afthemes.com/storeship-pro/fashion/"
        },
        "furniture": {
          "name": "Furniture Pro",
          "catgory": "Furniture",
          "slug": "furniture",
          "preview": "https://demo.afthemes.com/storeship-pro/furniture/"
        },
        "restaurant": {
          "name": "Restaurant Pro",
          "catgory": "Food and Beverage",
          "slug": "restaurant",
          "preview": "https://demo.afthemes.com/storeship-pro/restaurant/"
        }
      }
    },
    "kreeti-lite": {
      "data": "kreeti-lite",
      "free": "",
      "premium": "kreeti",
      "demodata": {
        "default": {
          "name": "Kreeti Lite",
          "catgory": "General",
          "slug": "kreeti-lite",
          "preview": "https://demo.afthemes.com/kreeti-lite/"
        },
        "fashion": {
          "name": "Fashion",
          "catgory": "Fashion",
          "slug": "fashion",
          "preview": "https://demo.afthemes.com/kreeti-lite/fashion/"
        },
        "sport": {
          "name": "Sport",
          "catgory": "Sport",
          "slug": "sport",
          "preview": "https://demo.afthemes.com/kreeti-lite/sport/"
        },
        "gadgets": {
          "name": "Gadgets",
          "catgory": "Business",
          "slug": "gadgets",
          "preview": "https://demo.afthemes.com/kreeti-lite/gadgets/"
        },
        "wedding": {
          "name": "Wedding",
          "catgory": "Blog",
          "slug": "wedding",
          "preview": "https://demo.afthemes.com/kreeti-lite/wedding/"
        }
      }
    },
    "kreeti": {
      "data": "kreeti",
      "free": "kreeti-lite",
      "premium": "",
      "demodata": {
        "default": {
          "name": "Kreeti",
          "catgory": "General",
          "slug": "kreeti",
          "preview": "https://demo.afthemes.com/kreeti/"
        },
        "dark": {
          "name": "Dark Pro",
          "catgory": "General",
          "slug": "dark",
          "preview": "https://demo.afthemes.com/kreeti/dark/"
        },
        "fashion": {
          "name": "Fashion Pro",
          "catgory": "Fashion",
          "slug": "fashion",
          "preview": "https://demo.afthemes.com/kreeti/fashion/"
        },
        "sport": {
          "name": "Sport Pro",
          "catgory": "Sport",
          "slug": "sport",
          "preview": "https://demo.afthemes.com/kreeti/sport/"
        },
        "recipe": {
          "name": "Recipe Pro",
          "catgory": "Blog",
          "slug": "recipe",
          "preview": "https://demo.afthemes.com/kreeti/recipe/"
        },
        "travel": {
          "name": "Travel Pro",
          "catgory": "Blog",
          "slug": "travel",
          "preview": "https://demo.afthemes.com/kreeti/travel/"
        },
        "wedding": {
          "name": "Wedding Pro",
          "catgory": "Blog",
          "slug": "wedding",
          "preview": "https://demo.afthemes.com/kreeti/wedding/"
        },
        "lifestyle": {
          "name": "Lifestyle Pro",
          "catgory": "Blog",
          "slug": "lifestyle",
          "preview": "https://demo.afthemes.com/kreeti/lifestyle/"
        }
      }
    },
    "enternews": {
      "data": "enternews",
      "free": "",
      "premium": "enternews-pro",
      "demodata": {
        "default": {
          "name": "EnterNews",
          "catgory": "General",
          "slug": "enternews",
          "preview": "https://demo.afthemes.com/enternews/"
        },
        "dark": {
          "name": "Dark",
          "catgory": "General",
          "slug": "dark",
          "preview": "https://demo.afthemes.com/enternews/dark/"
        },
        "covid-19": {
          "name": "Covid 19",
          "catgory": "Elementor",
          "slug": "covid-19",
          "preview": "https://demo.afthemes.com/enternews/covid-19/",
          "plugins": "elementor,elespare"
        },
        "sport": {
          "name": "Sport",
          "catgory": "Sport",
          "slug": "sport",
          "preview": "https://demo.afthemes.com/enternews/sport/"
        },
        "beauty": {
          "name": "Beauty",
          "catgory": "Elementor",
          "slug": "beauty",
          "preview": "https://demo.afthemes.com/enternews/beauty/",
          "plugins": "elementor,elespare"
        },
        "classic": {
          "name": "Classic",
          "catgory": "General",
          "slug": "classic",
          "preview": "https://demo.afthemes.com/enternews/classic/"
        },
        "crypto-news": {
          "name": "Crypto News",
          "catgory": "Elementor",
          "slug": "crypto-news",
          "preview": "https://demo.afthemes.com/enternews/crypto-news/",
          "plugins": "elementor,elespare"
        },
        "fashion": {
          "name": "Fashion",
          "catgory": "Fashion",
          "slug": "fashion",
          "preview": "https://demo.afthemes.com/enternews/fashion/"
        },
        "recipe": {
          "name": "Recipe",
          "catgory": "Blog",
          "slug": "recipe",
          "preview": "https://demo.afthemes.com/enternews/recipe/"
        },
        "lifestyle": {
          "name": "Lifestyle",
          "catgory": "Elementor",
          "slug": "lifestyle",
          "preview": "https://demo.afthemes.com/enternews/lifestyle/",
          "plugins": "elementor,elespare"
        },
        "crypto-currency": {
          "name": "Crypto Currency",
          "catgory": "Business",
          "slug": "crypto-currency",
          "preview": "https://demo.afthemes.com/enternews/crypto-currency/"
        },
        "arabic-news": {
          "name": "Arabic News",
          "catgory": "General",
          "slug": "arabic-news",
          "preview": "https://demo.afthemes.com/enternews/arabic-news/"
        },
        "china-news": {
          "name": "China News",
          "catgory": "General",
          "slug": "china-news",
          "preview": "https://demo.afthemes.com/enternews/china-news/"
        }
      }
    },
    "entermag": {
      "data": "entermag",
      "free": "enternews",
      "premium": "enternews-pro",
      "demodata": {
        "default": {
          "name": "EnterMag",
          "catgory": "General",
          "slug": "entermag",
          "preview": "https://demo.afthemes.com/enternews/entermag/"
        }
      }
    },
    "enternews-pro": {
      "data": "enternews-pro",
      "free": "enternews",
      "premium": "",
      "demodata": {
        "default": {
          "name": "EnterNews Pro",
          "catgory": "General",
          "slug": "enternews-pro",
          "preview": "https://demo.afthemes.com/enternews-pro/"
        },
        "light": {
          "name": "Light Pro",
          "catgory": "General",
          "slug": "light",
          "preview": "https://demo.afthemes.com/enternews-pro/light/"
        },
        "classic": {
          "name": "Classic Pro",
          "catgory": "General",
          "slug": "classic",
          "preview": "https://demo.afthemes.com/enternews-pro/classic/"
        },
        "dark": {
          "name": "Dark Pro",
          "catgory": "General",
          "slug": "dark",
          "preview": "https://demo.afthemes.com/enternews-pro/dark/"
        },
        "fashion": {
          "name": "Fashion Pro",
          "catgory": "Fashion",
          "slug": "fashion",
          "preview": "https://demo.afthemes.com/enternews-pro/fashion/"
        },
        "sport": {
          "name": "Sport Pro",
          "catgory": "Sport",
          "slug": "sport",
          "preview": "https://demo.afthemes.com/enternews-pro/sport/"
        },
        "online-news": {
          "name": "Online News",
          "catgory": "General",
          "slug": "online-news",
          "preview": "https://demo.afthemes.com/enternews-pro/online-news/"
        },
        "business": {
          "name": "Business Pro",
          "catgory": "Business",
          "slug": "business",
          "preview": "https://demo.afthemes.com/enternews-pro/business/"
        },
        "top-news": {
          "name": "Top News",
          "catgory": "General",
          "slug": "top-news",
          "preview": "https://demo.afthemes.com/enternews-pro/top-news/"
        },
        "recipe": {
          "name": "Recipe Pro",
          "catgory": "Blog",
          "slug": "recipe",
          "preview": "https://demo.afthemes.com/enternews-pro/recipe/"
        },
        "travel": {
          "name": "Travel Pro",
          "catgory": "Blog",
          "slug": "travel",
          "preview": "https://demo.afthemes.com/enternews-pro/travel/"
        },
        "general-news": {
          "name": "Lifestyle Pro",
          "catgory": "Blog",
          "slug": "general-news",
          "preview": "https://demo.afthemes.com/enternews-pro/general-news/"
        }
      }
    },
    "splashnews": {
      "data": "splashnews",
      "free": "darknews",
      "premium": "darknews-pro",
      "demodata": {
        "default": {
          "name": "SplashNews",
          "catgory": "Fashion",
          "slug": "splashnews",
          "preview": "https://demo.afthemes.com/darknews/splashnews/"
        }
      }
    },
    "darknews": {
      "data": "darknews",
      "free": "",
      "premium": "darknews-pro",
      "demodata": {
        "default": {
          "name": "DarkNews",
          "catgory": "General",
          "slug": "darknews",
          "preview": "https://demo.afthemes.com/darknews/"
        },
        "light": {
          "name": "Light",
          "catgory": "General",
          "slug": "light",
          "preview": "https://demo.afthemes.com/darknews/light/"
        },
        "sport": {
          "name": "Sport",
          "catgory": "Sport",
          "slug": "sport",
          "preview": "https://demo.afthemes.com/darknews/sport/"
        },
        "fashion": {
          "name": "Fashion",
          "catgory": "Fashion",
          "slug": "fashion",
          "preview": "https://demo.afthemes.com/darknews/fashion/"
        } ,
        "classic": {
          "name": "Classic",
          "catgory": "General",
          "slug": "classic",
          "preview": "https://demo.afthemes.com/darknews/classic/"
        },
        "gaming": {
          "name": "Gaming",
          "catgory": "Blog",
          "slug": "gaming",
          "preview": "https://demo.afthemes.com/darknews/gaming/"
        },
        "gym": {
          "name": "Gym",
          "catgory": "Elementor",
          "slug": "gym",
          "preview": "https://demo.afthemes.com/darknews/gym/",
          "plugins": "elementor,elespare"
        },
        "business": {
          "name": "Business",
          "catgory": "Elementor",
          "slug": "business",
          "preview": "https://demo.afthemes.com/darknews/business/",
          "plugins": "elementor,elespare"
        },
        "restaurant-blog": {
          "name": "Restaurant",
          "catgory": "Elementor",
          "slug": "restaurant-blog",
          "preview": "https://demo.afthemes.com/darknews/restaurant-blog/",
          "plugins": "elementor,elespare"
        },
        "tech-blog": {
          "name": "Tech Blog",
          "catgory": "Elementor",
          "slug": "tech-blog",
          "preview": "https://demo.afthemes.com/darknews/tech-blog/",
          "plugins": "elementor,elespare"
        },
        "retro-blog": {
          "name": "Retro Blog",
          "catgory": "Elementor",
          "slug": "retro-blog",
          "preview": "https://demo.afthemes.com/darknews/retro-blog/",
          "plugins": "elementor,elespare"
        },
        "crypto-news": {
          "name": "Crypto News",
          "catgory": "Business",
          "slug": "crypto-news",
          "preview": "https://demo.afthemes.com/darknews/crypto-news/"
        },
        "arabic-news": {
          "name": "Arabic News",
          "catgory": "General",
          "slug": "arabic-news",
          "preview": "https://demo.afthemes.com/darknews/arabic-news/"
        },
        "china-news": {
          "name": "China News",
          "catgory": "General",
          "slug": "china-news",
          "preview": "https://demo.afthemes.com/darknews/china-news/"
        }
      }
    },
    "darknews-pro": {
      "data": "darknews-pro",
      "free": "darknews",
      "premium": "",
      "demodata": {
        "default": {
          "name": "DarkNews Pro",
          "catgory": "General",
          "slug": "darknews-pro",
          "preview": "https://demo.afthemes.com/darknews-pro/"
        },
        "light": {
          "name": "Light Pro",
          "catgory": "General",
          "slug": "light",
          "preview": "https://demo.afthemes.com/darknews-pro/light/"
        },
        "classic": {
          "name": "Classic Pro",
          "catgory": "General",
          "slug": "classic",
          "preview": "https://demo.afthemes.com/darknews-pro/classic/"
        },
        "fashion": {
          "name": "Fashion Pro",
          "catgory": "Fashion",
          "slug": "fashion",
          "preview": "https://demo.afthemes.com/darknews-pro/fashion/"
        },
        "sport": {
          "name": "Sport Pro",
          "catgory": "Sport",
          "slug": "sport",
          "preview": "https://demo.afthemes.com/darknews-pro/sport/"
        },
        "business": {
          "name": "Business Pro",
          "catgory": "Business",
          "slug": "business",
          "preview": "https://demo.afthemes.com/darknews-pro/business/"
        },
        "travel": {
          "name": "Travel Pro",
          "catgory": "Blog",
          "slug": "travel",
          "preview": "https://demo.afthemes.com/darknews-pro/travel/"
        },
        "gaming": {
          "name": "Gaming Pro",
          "catgory": "Blog",
          "slug": "gaming",
          "preview": "https://demo.afthemes.com/darknews-pro/gaming/"
        },
        "gadgets": {
          "name": "Gadgets Pro",
          "catgory": "Blog",
          "slug": "gadgets",
          "preview": "https://demo.afthemes.com/darknews-pro/gadgets/"
        },
        "recipe": {
          "name": "Recipe Pro",
          "catgory": "Blog",
          "slug": "recipe",
          "preview": "https://demo.afthemes.com/darknews-pro/recipe/"
        },
        "fitness": {
          "name": "Fitness Pro",
          "catgory": "Blog",
          "slug": "fitness",
          "preview": "https://demo.afthemes.com/darknews-pro/fitness/"
        },
        "automobile": {
          "name": "Automobile Pro",
          "catgory": "Blog",
          "slug": "automobile",
          "preview": "https://demo.afthemes.com/darknews-pro/automobile/"
        },
        "crypto-news": {
          "name": "Crypto News",
          "catgory": "Business",
          "slug": "crypto-news",
          "preview": "https://demo.afthemes.com/darknews-pro/crypto-news/"
        },
        "arabic-news": {
          "name": "Arabic News",
          "catgory": "General",
          "slug": "arabic-news",
          "preview": "https://demo.afthemes.com/darknews-pro/arabic-news/"
        },
        "china-news": {
          "name": "Crypto News",
          "catgory": "Business",
          "slug": "china-news",
          "preview": "https://demo.afthemes.com/darknews-pro/china-news/"
        }
      }
    },
    "morenews": {
      "data": "morenews",
      "free": "",
      "premium": "morenews-pro",
      "demodata": {
        "default": {
          "name": "MoreNews",
          "catgory": "General",
          "slug": "morenews",
          "preview": "https://demo.afthemes.com/morenews/"
        },
        "sport": {
          "name": "Sport",
          "catgory": "Sport",
          "slug": "sport",
          "preview": "https://demo.afthemes.com/morenews/sport/"
        },
        "fashion": {
          "name": "Fashion",
          "catgory": "Fashion",
          "slug": "fashion",
          "preview": "https://demo.afthemes.com/morenews/fashion/"
        },
        "food-recipe": {
          "name": "Food and Recipe",
          "catgory": "Blog",
          "slug": "food-recipe",
          "preview": "https://demo.afthemes.com/morenews/food-recipe/"
        },
        "travel": {
          "name": "Travel",
          "catgory": "Blog",
          "slug": "travel",
          "preview": "https://demo.afthemes.com/morenews/travel/"
        },
        "crypto-news": {
          "name": "Crypto News",
          "catgory": "Business",
          "slug": "crypto-news",
          "preview": "https://demo.afthemes.com/morenews/crypto-news/"
        },
        "arabic-news": {
          "name": "Arabic News",
          "catgory": "General",
          "slug": "arabic-news",
          "preview": "https://demo.afthemes.com/morenews/arabic-news/"
        },
        "china-today": {
          "name": "China Today",
          "catgory": "General",
          "slug": "china-today",
          "preview": "https://demo.afthemes.com/morenews/china-today/"
        },
        "architecture-blog": {
          "name": "Architecture Blog",
          "catgory": "Elementor",
          "slug": "architecture-blog",
          "preview": "https://demo.afthemes.com/morenews/architecture-blog/",
          "plugins": "elementor,elespare"
        },
        "beauty-studio": {
          "name": "Beauty Studio",
          "catgory": "Elementor",
          "slug": "beauty-studio",
          "preview": "https://demo.afthemes.com/morenews/beauty-studio/",
          "plugins": "elementor,elespare"
        },
        "esport": {
          "name": "Esport",
          "catgory": "Elementor",
          "slug": "esport",
          "preview": "https://demo.afthemes.com/morenews/esport/",
          "plugins": "elementor,elespare"
        },
        "local-business": {
          "name": "Local Business",
          "catgory": "Elementor",
          "slug": "local-business",
          "preview": "https://demo.afthemes.com/morenews/local-business/",
          "plugins": "elementor,elespare"
        },
        "real-estate": {
          "name": "Real Estate",
          "catgory": "Elementor",
          "slug": "real-estate",
          "preview": "https://demo.afthemes.com/morenews/real-estate/",
          "plugins": "elementor,elespare"
        }
      }
    },
    "morenews-pro": {
      "data": "morenews-pro",
      "free": "morenews",
      "premium": "",
      "demodata": {
        "default": {
          "name": "MoreNews Pro",
          "catgory": "General",
          "slug": "morenews-pro",
          "preview": "https://demo.afthemes.com/morenews-pro/"
        },
        "classic": {
          "name": "Classic Pro",
          "catgory": "General",
          "slug": "classic",
          "preview": "https://demo.afthemes.com/morenews-pro/classic/"
        },
        "fashion": {
          "name": "Fashion Pro",
          "catgory": "Fashion",
          "slug": "fashion",
          "preview": "https://demo.afthemes.com/morenews-pro/fashion/"
        },
        "sport": {
          "name": "Sport Pro",
          "catgory": "Sport",
          "slug": "dark",
          "preview": "https://demo.afthemes.com/morenews-pro/dark/"
        },
        "business": {
          "name": "Crypto News Pro",
          "catgory": "Business",
          "slug": "crypto-news",
          "preview": "https://demo.afthemes.com/morenews-pro/crypto-news/"
        },
        "travel": {
          "name": "Travel Pro",
          "catgory": "Blog",
          "slug": "travel",
          "preview": "https://demo.afthemes.com/morenews-pro/travel/"
        },
        "recipe": {
          "name": "Food and Recipe Pro",
          "catgory": "Blog",
          "slug": "food-recipe",
          "preview": "https://demo.afthemes.com/morenews-pro/food-recipe/"
        },
        "fitness": {
          "name": "Fitness Magazine Pro",
          "catgory": "Blog",
          "slug": "fitness-magazine",
          "preview": "https://demo.afthemes.com/morenews-pro/fitness-magazine/"
        },
        "arabic-news": {
          "name": "Arabic News",
          "catgory": "General",
          "slug": "arabic-news",
          "preview": "https://demo.afthemes.com/morenews-pro/arabic-news/"
        },
        "china-today": {
          "name": "China Today",
          "catgory": "General",
          "slug": "china-today",
          "preview": "https://demo.afthemes.com/morenews-pro/china-today/"
        }
      }
    },
    "shopical": {
      "data": "shopical",
      "free": "",
      "premium": "shopical-pro",
      "demodata": {
        "default": {
          "name": "Shopical",
          "catgory": "General",
          "slug": "shopical",
          "preview": "https://demo.afthemes.com/shopical/"
        },
        "automobile": {
          "name": "Automobile",
          "catgory": "Automobile",
          "slug": "automobile",
          "preview": "https://demo.afthemes.com/shopical/automobile/"
        }
      }
    },
    "shopical-pro": {
      "data": "shopical-pro",
      "free": "shopical",
      "premium": "",
      "demodata": {
        "default": {
          "name": "Shopical Pro",
          "catgory": "General",
          "slug": "shopical-pro",
          "preview": "https://demo.afthemes.com/shopical-pro/"
        },
        "gadgets-pro": {
          "name": "Gadgets Pro",
          "catgory": "Gadgets",
          "slug": "gadgets-pro",
          "preview": "https://demo.afthemes.com/shopical-pro/gadgets-pro/"
        }
      }
    },
    "shopage": {
      "data": "shopage",
      "free": "shopical",
      "premium": "shopical-pro",
      "demodata": {
        "default": {
          "name": "Shopage",
          "catgory": "General",
          "slug": "shopage",
          "preview": "https://demo.afthemes.com/shopical/shopage/"
        }
      }
    },
    "magnitude": {
      "data": "magnitude",
      "free": "",
      "premium": "magnitude-pro",
      "demodata": {
        "default": {
          "name": "Magnitude",
          "catgory": "General",
          "slug": "magnitude",
          "preview": "https://demo.afthemes.com/magnitude/"
        },
        "sport": {
          "name": "Sport",
          "catgory": "Sport",
          "slug": "sport",
          "preview": "https://demo.afthemes.com/magnitude/sport/"
        },
        "newsportal": {
          "name": "Newsportal",
          "catgory": "General",
          "slug": "newsportal",
          "preview": "https://demo.afthemes.com/magnitude/newsportal/"
        }
      }
    },
    "magnitude-pro": {
      "data": "magnitude-pro",
      "free": "magnitude",
      "premium": "",
      "demodata": {
        "default": {
          "name": "Magnitude-pro",
          "catgory": "General",
          "slug": "magnitude-pro",
          "preview": "https://demo.afthemes.com/magnitude-pro/"
        },
        "sport-pro": {
          "name": "Sport Pro",
          "catgory": "Sport",
          "slug": "sport-pro",
          "preview": "https://demo.afthemes.com/magnitude-pro/sport-pro/"
        },
        "newsportal-pro": {
          "name": "Newsportal Pro",
          "catgory": "General",
          "slug": "newsportal-pro",
          "preview": "https://demo.afthemes.com/magnitude-pro/newsportal-pro/"
        },
        "magnitude-dark": {
          "name": "Magnitude Dark",
          "catgory": "Dark",
          "slug": "magnitude-dark",
          "preview": "https://demo.afthemes.com/magnitude-pro/magnitude-dark/"
        },
        "gadgets-pro": {
          "name": "Gadgets Pro",
          "catgory": "Business",
          "slug": "gadgets-pro",
          "preview": "https://demo.afthemes.com/magnitude-pro/gadgets-pro/"
        }
      }
    },
    "magazine-7": {
      "data": "magazine-7",
      "free": "",
      "premium": "magazine-7-plus",
      "demodata": {
        "default": {
          "name": "Magazine 7",
          "catgory": "General",
          "slug": "magazine-7",
          "preview": "https://demo.afthemes.com/magazine-7/"
        },
        "restro": {
          "name": "Restro",
          "catgory": "Blog",
          "slug": "restro",
          "preview": "https://demo.afthemes.com/magazine-7/restro/"
        }
      }
    },
    "magazine-7-plus": {
      "data": "magazine-7-plus",
      "free": "magazine-7",
      "premium": "",
      "demodata": {
        "default": {
          "name": "Magazine 7-plus",
          "catgory": "General",
          "slug": "magazine-7-plus",
          "preview": "https://demo.afthemes.com/magazine-7-plus/"
        },
        "restro": {
          "name": "Restro",
          "catgory": "Blog",
          "slug": "restro",
          "preview": "https://demo.afthemes.com/magazine-7-plus/restro/"
        },
        "photography": {
          "name": "Photography",
          "catgory": "Blog",
          "slug": "photography",
          "preview": "https://demo.afthemes.com/magazine-7-plus/photography/"
        },
        "minimal-mag": {
          "name": "Minimal Mag",
          "catgory": "Blog",
          "slug": "minimal-mag",
          "preview": "https://demo.afthemes.com/magazine-7-plus/minimal-mag/"
        },
        "mag-shop": {
          "name": "Mag Shop",
          "catgory": "Shop",
          "slug": "mag-shop",
          "preview": "https://demo.afthemes.com/magazine-7-plus/mag-shop/"
        }
      }
    },
    "beautiful-blog": {
      "data": "beautiful-blog",
      "free": "magazine-7",
      "premium": "magazine-7-plus",
      "demodata": {
        "default": {
          "name": "Beautiful Blog",
          "catgory": "Blog",
          "slug": "beautiful-blog",
          "preview": "https://demo.afthemes.com/magazine-7/beautiful-blog/"
        }
      }
    },
    "newstorial": {
      "data": "newstorial",
      "free": "magazine-7",
      "premium": "magazine-7-plus",
      "demodata": {
        "default": {
          "name": "Newstorial",
          "catgory": "General",
          "slug": "newstorial",
          "preview": "https://demo.afthemes.com/magazine-7/newstorial/"
        }
      }
    },
    "magaziness": {
      "data": "magaziness",
      "free": "magazine-7",
      "premium": "magazine-7-plus",
      "demodata": {
        "default": {
          "name": "Magaziness",
          "catgory": "General",
          "slug": "magaziness",
          "preview": "https://demo.afthemes.com/magazine-7/magaziness/"
        }
      }
    },
    "storekeeper": {
      "data": "storekeeper",
      "free": "storecommerce",
      "premium": "storecommerce-pro",
      "demodata": {
        "default": {
          "name": "Storekeeper",
          "catgory": "General",
          "slug": "storekeeper",
          "preview": "https://demo.afthemes.com/storecommerce/storekeeper/"
        }
      }
    },
    "storecommerce": {
      "data": "storecommerce",
      "free": "",
      "premium": "storecommerce-pro",
      "demodata": {
        "default": {
          "name": "Storecommerce",
          "catgory": "General",
          "slug": "storecommerce",
          "preview": "https://demo.afthemes.com/storecommerce/"
        },
        "gadgets": {
          "name": "Gadgets",
          "catgory": "Gadgets",
          "slug": "gadgets",
          "preview": "https://demo.afthemes.com/storecommerce/gadgets"
        },
        "interior": {
          "name": "Interior",
          "catgory": "Interior",
          "slug": "interior",
          "preview": "https://demo.afthemes.com/storecommerce/interior"
        }
      }
    },
    "storecommerce-pro": {
      "data": "storecommerce-pro",
      "free": "storecommerce",
      "premium": "",
      "demodata": {
        "default": {
          "name": "Storecommerce Pro",
          "catgory": "General",
          "slug": "storecommerce-pro",
          "preview": "https://demo.afthemes.com/storecommerce-pro/"
        },
        "gadgets-pro": {
          "name": "Gadgets Pro",
          "catgory": "Gadgets",
          "slug": "gadgets-pro",
          "preview": "https://demo.afthemes.com/storecommerce-pro/gadgets-pro"
        },
        "interior-pro": {
          "name": "Interior Pro",
          "catgory": "Interior",
          "slug": "interior-pro",
          "preview": "https://demo.afthemes.com/storecommerce-pro/interior-pro"
        },
        "automobile-pro": {
          "name": "Automobile Pro",
          "catgory": "Automobile",
          "slug": "automobile-pro",
          "preview": "https://demo.afthemes.com/storecommerce-pro/automobile-pro"
        },
        "just-food-pro": {
          "name": "Just Food Pro",
          "catgory": "Food",
          "slug": "just-food-pro",
          "preview": "https://demo.afthemes.com/storecommerce-pro/just-food-pro"
        }
      }
    },
    "vivacious-magazine": {
      "data": "vivacious-magazine",
      "free": "elegant-magazine",
      "premium": "elegant-magazine-pro",
      "demodata": {
        "default": {
          "name": "Vivacious Magazine",
          "catgory": "Fashion",
          "slug": "vivacious-magazine",
          "preview": "https://demo.afthemes.com/elegant-magazine/vivacious-magazine/"
        }
      }
    },
    "magnificent-blog": {
      "data": "magnificent-blog",
      "free": "elegant-magazine",
      "premium": "elegant-magazine-pro",
      "demodata": {
        "default": {
          "name": "Magnificent Blog",
          "catgory": "Blog",
          "slug": "magnificent-blog",
          "preview": "https://demo.afthemes.com/elegant-magazine/magnificent-blog/"
        }
      }
    },    
    "daily-magazine": {
      "data": "daily-magazine",
      "free": "elegant-magazine",
      "premium": "elegant-magazine-pro",
      "demodata": {
        "default": {
          "name": "Daily Magazine",
          "catgory": "General",
          "slug": "daily-magazine",
          "preview": "https://demo.afthemes.com/elegant-magazine/daily-magazine/"
        }
      }
    },
    "elegant-magazine": {
      "data": "elegant-magazine",
      "free": "",
      "premium": "elegant-magazine-pro",
      "demodata": {
        "default": {
          "name": "Elegant Magazine",
          "catgory": "General",
          "slug": "elegant-magazine",
          "preview": "https://demo.afthemes.com/elegant-magazine/"
        },
        "fashion": {
          "name": "Fashion",
          "catgory": "Fashion",
          "slug": "fashion",
          "preview": "https://demo.afthemes.com/elegant-magazine/fashion/"
        },
        "minimal": {
          "name": "Minimal",
          "catgory": "Blog",
          "slug": "minimal",
          "preview": "https://demo.afthemes.com/elegant-magazine/minimal/"
        },
        "newsportal": {
          "name": "Newsportal",
          "catgory": "General",
          "slug": "newsportal",
          "preview": "https://demo.afthemes.com/elegant-magazine/newsportal/"
        },
        "travel-blog": {
          "name": "Travel Blog",
          "catgory": "Blog",
          "slug": "travel-blog",
          "preview": "https://demo.afthemes.com/elegant-magazine/travel-blog/"
        }
      }
    },
    "elegant-magazine-pro": {
      "data": "elegant-magazine-pro",
      "free": "elegant-magazine",
      "premium": "",
      "demodata": {
        "default": {
          "name": "Elegant Magazine Pro",
          "catgory": "General",
          "slug": "elegant-magazine-pro",
          "preview": "https://demo.afthemes.com/elegant-magazine-pro/"
        },
        "fashion-boxed": {
          "name": "Fashion Boxed",
          "catgory": "Fashion",
          "slug": "fashion-boxed",
          "preview": "https://demo.afthemes.com/elegant-magazine-pro/fashion-boxed/"
        },
        "minimal": {
          "name": "Minimal",
          "catgory": "Blog",
          "slug": "minimal",
          "preview": "https://demo.afthemes.com/elegant-magazine-pro/minimal/"
        },
        "newsportal": {
          "name": "Newsportal",
          "catgory": "General",
          "slug": "newsportal",
          "preview": "https://demo.afthemes.com/elegant-magazine-pro/newsportal/"
        },
        "newsportal-boxed": {
          "name": "Newsportal Boxed",
          "catgory": "General",
          "slug": "newsportal-boxed",
          "preview": "https://demo.afthemes.com/elegant-magazine-pro/newsportal-boxed/"
        },
        "travel-blog": {
          "name": "Travel Blog",
          "catgory": "Blog",
          "slug": "travel-blog",
          "preview": "https://demo.afthemes.com/elegant-magazine-pro/travel-blog/"
        },
        "photography": {
          "name": "Photography",
          "catgory": "Blog",
          "slug": "photography",
          "preview": "https://demo.afthemes.com/elegant-magazine-pro/photography/"
        }
      }
    }        
  }
} 
